CHANGES.txt
LICENSE.txt
MANIFEST.in
README.txt
bootstrap.py
buildout.cfg
setup.py
src/m01/__init__.py
src/m01.logger.egg-info/PKG-INFO
src/m01.logger.egg-info/SOURCES.txt
src/m01.logger.egg-info/dependency_links.txt
src/m01.logger.egg-info/namespace_packages.txt
src/m01.logger.egg-info/not-zip-safe
src/m01.logger.egg-info/requires.txt
src/m01.logger.egg-info/top_level.txt
src/m01/logger/README.txt
src/m01/logger/__init__.py
src/m01/logger/capacity.txt
src/m01/logger/formatter.py
src/m01/logger/handler.py
src/m01/logger/testing.py
src/m01/logger/tests.py